{"cameraMode":{"drawMode":0,"name":"Shaded","section":"Shading Mode"},"sceneLighting":true,"audioPlay":false,"sceneViewState":{"m_AlwaysRefresh":false,"showFog":true,"showSkybox":true,"showFlares":true,"showImageEffects":true,"showParticleSystems":true,"showVisualEffectGraphs":true,"m_FxEnabled":true},"in2DMode":false,"pivot":{"x":3.583562135696411,"y":-86.6663818359375,"z":26.82814598083496},"rotation":{"x":0.5959411859512329,"y":0.03920882195234299,"z":-0.029135379940271379,"w":0.801575779914856},"size":53.97236251831055,"orthographic":false}